{
    "frame_0000.jpg": {
        "probability": 0.011817730963230133
    },
    "frame_0001.jpg": {
        "probability": 0.019697114825248718
    },
    "frame_0002.jpg": {
        "probability": 0.008951603434979916
    },
    "frame_0003.jpg": {
        "probability": 0.006287503521889448
    },
    "frame_0004.jpg": {
        "probability": 0.0062981960363686085
    },
    "frame_0005.jpg": {
        "probability": 0.008417326025664806
    },
    "frame_0006.jpg": {
        "probability": 0.007119324989616871
    },
    "frame_0007.jpg": {
        "probability": 0.006418066564947367
    },
    "frame_0008.jpg": {
        "probability": 0.008139512501657009
    },
    "frame_0009.jpg": {
        "probability": 0.009856415912508965
    },
    "frame_0010.jpg": {
        "probability": 0.004090123809874058
    },
    "frame_0011.jpg": {
        "probability": 0.004759347066283226
    },
    "frame_0012.jpg": {
        "probability": 0.0027333844918757677
    },
    "frame_0013.jpg": {
        "probability": 0.0034466783981770277
    },
    "frame_0014.jpg": {
        "probability": 0.002051845658570528
    },
    "frame_0015.jpg": {
        "probability": 0.0011560677085071802
    },
    "frame_0016.jpg": {
        "probability": 0.001517514348961413
    },
    "frame_0017.jpg": {
        "probability": 0.003900734009221196
    },
    "frame_0018.jpg": {
        "probability": 0.00517291622236371
    },
    "frame_0019.jpg": {
        "probability": 0.00465884106233716
    },
    "frame_0020.jpg": {
        "probability": 0.00427808053791523
    },
    "frame_0021.jpg": {
        "probability": 0.003340502269566059
    },
    "frame_0022.jpg": {
        "probability": 0.0070335716009140015
    },
    "frame_0023.jpg": {
        "probability": 0.0061368937604129314
    },
    "frame_0024.jpg": {
        "probability": 0.00273236189968884
    },
    "frame_0025.jpg": {
        "probability": 0.003363789524883032
    },
    "frame_0026.jpg": {
        "probability": 0.003239547135308385
    },
    "frame_0027.jpg": {
        "probability": 0.0035222803708165884
    },
    "frame_0028.jpg": {
        "probability": 0.0024806868750602007
    },
    "frame_0029.jpg": {
        "probability": 0.003278853837400675
    },
    "frame_0030.jpg": {
        "probability": 0.0031031761318445206
    },
    "frame_0031.jpg": {
        "probability": 0.004136750474572182
    },
    "frame_0032.jpg": {
        "probability": 0.003977461252361536
    },
    "frame_0033.jpg": {
        "probability": 0.004494932480156422
    },
    "frame_0034.jpg": {
        "probability": 0.0032453667372465134
    },
    "frame_0035.jpg": {
        "probability": 0.004401382990181446
    },
    "frame_0036.jpg": {
        "probability": 0.004315235186368227
    },
    "frame_0037.jpg": {
        "probability": 0.0044146268628537655
    },
    "frame_0038.jpg": {
        "probability": 0.004208364058285952
    },
    "frame_0039.jpg": {
        "probability": 0.005245161708444357
    },
    "frame_0040.jpg": {
        "probability": 0.00363534246571362
    },
    "frame_0041.jpg": {
        "probability": 0.005190133582800627
    },
    "frame_0042.jpg": {
        "probability": 0.004614687524735928
    },
    "frame_0043.jpg": {
        "probability": 0.004395123105496168
    },
    "frame_0044.jpg": {
        "probability": 0.004995245486497879
    },
    "frame_0045.jpg": {
        "probability": 0.002868252107873559
    },
    "frame_0046.jpg": {
        "probability": 0.0009569601388648152
    },
    "frame_0047.jpg": {
        "probability": 0.0014305183431133628
    },
    "frame_0048.jpg": {
        "probability": 0.0006060583982616663
    },
    "frame_0049.jpg": {
        "probability": 0.002128358231857419
    },
    "frame_0050.jpg": {
        "probability": 0.003075310029089451
    },
    "frame_0051.jpg": {
        "probability": 0.0023636510595679283
    },
    "frame_0052.jpg": {
        "probability": 0.016061436384916306
    },
    "frame_0053.jpg": {
        "probability": 0.015553713776171207
    },
    "frame_0054.jpg": {
        "probability": 0.007739316672086716
    },
    "frame_0055.jpg": {
        "probability": 0.004635381978005171
    },
    "frame_0056.jpg": {
        "probability": 0.002763977739959955
    },
    "frame_0057.jpg": {
        "probability": 0.00280940905213356
    },
    "frame_0058.jpg": {
        "probability": 0.002035752637311816
    },
    "frame_0059.jpg": {
        "probability": 0.0010970989242196083
    },
    "frame_0060.jpg": {
        "probability": 0.0015834287041798234
    },
    "frame_0061.jpg": {
        "probability": 0.002178617985919118
    },
    "frame_0062.jpg": {
        "probability": 0.0016948459669947624
    },
    "frame_0063.jpg": {
        "probability": 0.0027297502383589745
    },
    "frame_0064.jpg": {
        "probability": 0.0023261860478669405
    },
    "frame_0065.jpg": {
        "probability": 0.0015087841311469674
    },
    "frame_0066.jpg": {
        "probability": 0.0016065937234088778
    },
    "frame_0067.jpg": {
        "probability": 0.0012125803623348475
    },
    "frame_0068.jpg": {
        "probability": 0.0008756645838730037
    },
    "frame_0069.jpg": {
        "probability": 0.0006813285290263593
    },
    "frame_0070.jpg": {
        "probability": 0.0008385265246033669
    },
    "frame_0071.jpg": {
        "probability": 0.0007919227937236428
    },
    "frame_0072.jpg": {
        "probability": 0.0004234961816109717
    },
    "frame_0073.jpg": {
        "probability": 0.0004801830218639225
    },
    "frame_0074.jpg": {
        "probability": 0.0005493249627761543
    },
    "frame_0075.jpg": {
        "probability": 0.0007029095431789756
    },
    "frame_0076.jpg": {
        "probability": 0.00071374123217538
    },
    "frame_0077.jpg": {
        "probability": 0.0006703971303068101
    },
    "frame_0078.jpg": {
        "probability": 0.0006980157922953367
    },
    "frame_0079.jpg": {
        "probability": 0.0009764963760972023
    },
    "frame_0080.jpg": {
        "probability": 0.002221004804596305
    },
    "frame_0081.jpg": {
        "probability": 0.0009363965946249664
    },
    "frame_0082.jpg": {
        "probability": 0.00133607629686594
    },
    "frame_0083.jpg": {
        "probability": 0.0014667670475319028
    },
    "frame_0084.jpg": {
        "probability": 0.001058106659911573
    },
    "frame_0085.jpg": {
        "probability": 0.0011133780935779214
    },
    "frame_0086.jpg": {
        "probability": 0.001793127739802003
    },
    "frame_0087.jpg": {
        "probability": 0.0016136373160406947
    },
    "frame_0088.jpg": {
        "probability": 0.0015903603052720428
    },
    "frame_0089.jpg": {
        "probability": 0.0016983947716653347
    },
    "frame_0090.jpg": {
        "probability": 0.0015811921330168843
    },
    "frame_0091.jpg": {
        "probability": 0.0015788302989676595
    },
    "frame_0092.jpg": {
        "probability": 0.001681396970525384
    },
    "frame_0093.jpg": {
        "probability": 0.0017075375653803349
    },
    "frame_0094.jpg": {
        "probability": 0.00441631069406867
    },
    "frame_0095.jpg": {
        "probability": 0.0028487362433224916
    },
    "frame_0096.jpg": {
        "probability": 0.005222037900239229
    },
    "frame_0097.jpg": {
        "probability": 0.005462180357426405
    },
    "frame_0098.jpg": {
        "probability": 0.006709955167025328
    },
    "frame_0099.jpg": {
        "probability": 0.002380920806899667
    },
    "frame_0100.jpg": {
        "probability": 0.004826846532523632
    },
    "frame_0101.jpg": {
        "probability": 0.005467918235808611
    },
    "frame_0102.jpg": {
        "probability": 0.006975934375077486
    },
    "frame_0103.jpg": {
        "probability": 0.032729558646678925
    },
    "frame_0104.jpg": {
        "probability": 0.02288706600666046
    },
    "frame_0105.jpg": {
        "probability": 0.024586031213402748
    },
    "frame_0106.jpg": {
        "probability": 0.019185377284884453
    },
    "frame_0107.jpg": {
        "probability": 0.01308091264218092
    },
    "frame_0108.jpg": {
        "probability": 0.010696496814489365
    },
    "frame_0109.jpg": {
        "probability": 0.007225772365927696
    },
    "frame_0110.jpg": {
        "probability": 0.008778386749327183
    },
    "frame_0111.jpg": {
        "probability": 0.006438490003347397
    },
    "frame_0112.jpg": {
        "probability": 0.0047569856978952885
    },
    "frame_0113.jpg": {
        "probability": 0.0036364325787872076
    },
    "frame_0114.jpg": {
        "probability": 0.005645652301609516
    },
    "frame_0115.jpg": {
        "probability": 0.008412361145019531
    },
    "frame_0116.jpg": {
        "probability": 0.010803481563925743
    },
    "frame_0117.jpg": {
        "probability": 0.011614838615059853
    },
    "frame_0118.jpg": {
        "probability": 0.008614765480160713
    },
    "frame_0119.jpg": {
        "probability": 0.005731499288231134
    },
    "frame_0120.jpg": {
        "probability": 0.0037965490482747555
    },
    "frame_0121.jpg": {
        "probability": 0.004680756013840437
    },
    "frame_0122.jpg": {
        "probability": 0.0038740490563213825
    },
    "frame_0123.jpg": {
        "probability": 0.0032492992468178272
    },
    "frame_0124.jpg": {
        "probability": 0.0026187144685536623
    },
    "frame_0125.jpg": {
        "probability": 0.004745981190353632
    },
    "frame_0126.jpg": {
        "probability": 0.004690687172114849
    },
    "frame_0127.jpg": {
        "probability": 0.00114995869807899
    },
    "frame_0128.jpg": {
        "probability": 0.0007702384609729052
    },
    "frame_0129.jpg": {
        "probability": 0.0014429977163672447
    },
    "frame_0130.jpg": {
        "probability": 0.0015446424949914217
    },
    "frame_0131.jpg": {
        "probability": 0.0020956036169081926
    },
    "frame_0132.jpg": {
        "probability": 0.003144874470308423
    },
    "frame_0133.jpg": {
        "probability": 0.00436215428635478
    },
    "frame_0134.jpg": {
        "probability": 0.00451700622215867
    },
    "frame_0135.jpg": {
        "probability": 0.0027560307644307613
    },
    "frame_0136.jpg": {
        "probability": 0.004416474141180515
    },
    "frame_0137.jpg": {
        "probability": 0.004091418348252773
    },
    "frame_0138.jpg": {
        "probability": 0.0017401518998667598
    },
    "frame_0139.jpg": {
        "probability": 0.0024914038367569447
    },
    "frame_0140.jpg": {
        "probability": 0.0020204209722578526
    },
    "frame_0141.jpg": {
        "probability": 0.001105220173485577
    },
    "frame_0142.jpg": {
        "probability": 0.003581796307116747
    },
    "frame_0143.jpg": {
        "probability": 0.002190303523093462
    },
    "frame_0144.jpg": {
        "probability": 0.010995390824973583
    },
    "frame_0145.jpg": {
        "probability": 0.008169174194335938
    },
    "frame_0146.jpg": {
        "probability": 0.005441823974251747
    },
    "frame_0147.jpg": {
        "probability": 0.012992087751626968
    },
    "frame_0148.jpg": {
        "probability": 0.025071507319808006
    },
    "frame_0149.jpg": {
        "probability": 0.02530096098780632
    },
    "frame_0150.jpg": {
        "probability": 0.05077604949474335
    },
    "frame_0151.jpg": {
        "probability": 0.051347192376852036
    },
    "frame_0152.jpg": {
        "probability": 0.0399479940533638
    },
    "frame_0153.jpg": {
        "probability": 0.03744715452194214
    },
    "frame_0154.jpg": {
        "probability": 0.05548156797885895
    },
    "frame_0155.jpg": {
        "probability": 0.042984507977962494
    },
    "frame_0156.jpg": {
        "probability": 0.08025328814983368
    },
    "frame_0157.jpg": {
        "probability": 0.03363475576043129
    },
    "frame_0158.jpg": {
        "probability": 0.031545717269182205
    },
    "frame_0159.jpg": {
        "probability": 0.030077459290623665
    },
    "frame_0160.jpg": {
        "probability": 0.026154611259698868
    },
    "frame_0161.jpg": {
        "probability": 0.016692396253347397
    },
    "frame_0162.jpg": {
        "probability": 0.025803131982684135
    },
    "frame_0163.jpg": {
        "probability": 0.015570076182484627
    },
    "frame_0164.jpg": {
        "probability": 0.022936439141631126
    },
    "frame_0165.jpg": {
        "probability": 0.020822497084736824
    },
    "frame_0166.jpg": {
        "probability": 0.02769923396408558
    },
    "frame_0167.jpg": {
        "probability": 0.019310496747493744
    },
    "frame_0168.jpg": {
        "probability": 0.00829768180847168
    },
    "frame_0169.jpg": {
        "probability": 0.010807580314576626
    },
    "frame_0170.jpg": {
        "probability": 0.018883736804127693
    },
    "frame_0171.jpg": {
        "probability": 0.008765379898250103
    },
    "frame_0172.jpg": {
        "probability": 0.004430987872183323
    },
    "frame_0173.jpg": {
        "probability": 0.014322347939014435
    },
    "frame_0174.jpg": {
        "probability": 0.013897673226892948
    },
    "frame_0175.jpg": {
        "probability": 0.009153896942734718
    },
    "frame_0176.jpg": {
        "probability": 0.005624664016067982
    },
    "frame_0177.jpg": {
        "probability": 0.004427015781402588
    },
    "frame_0178.jpg": {
        "probability": 0.03648260235786438
    },
    "frame_0179.jpg": {
        "probability": 0.047150466591119766
    },
    "frame_0180.jpg": {
        "probability": 0.014228074811398983
    },
    "frame_0181.jpg": {
        "probability": 0.004157593939453363
    },
    "frame_0182.jpg": {
        "probability": 0.0032485625706613064
    },
    "frame_0183.jpg": {
        "probability": 0.003860140684992075
    },
    "frame_0184.jpg": {
        "probability": 0.006936463061720133
    },
    "frame_0185.jpg": {
        "probability": 0.006200724747031927
    },
    "frame_0186.jpg": {
        "probability": 0.0064221820794045925
    },
    "frame_0187.jpg": {
        "probability": 0.0062905666418373585
    },
    "frame_0188.jpg": {
        "probability": 0.008964892476797104
    },
    "frame_0189.jpg": {
        "probability": 0.029309015721082687
    },
    "frame_0190.jpg": {
        "probability": 0.03896692767739296
    },
    "frame_0191.jpg": {
        "probability": 0.03550437465310097
    },
    "frame_0192.jpg": {
        "probability": 0.007602422498166561
    },
    "frame_0193.jpg": {
        "probability": 0.008488151244819164
    },
    "frame_0194.jpg": {
        "probability": 0.013390738517045975
    },
    "frame_0195.jpg": {
        "probability": 0.02595333568751812
    },
    "frame_0196.jpg": {
        "probability": 0.028325766324996948
    },
    "frame_0197.jpg": {
        "probability": 0.018355395644903183
    },
    "frame_0198.jpg": {
        "probability": 0.018377378582954407
    },
    "frame_0199.jpg": {
        "probability": 0.022010087966918945
    },
    "frame_0200.jpg": {
        "probability": 0.0893203467130661
    },
    "frame_0201.jpg": {
        "probability": 0.04227050766348839
    },
    "frame_0202.jpg": {
        "probability": 0.06333507597446442
    },
    "frame_0203.jpg": {
        "probability": 0.09864193201065063
    },
    "frame_0204.jpg": {
        "probability": 0.11149206757545471
    },
    "frame_0205.jpg": {
        "probability": 0.11902215331792831
    },
    "frame_0206.jpg": {
        "probability": 0.07503415644168854
    },
    "frame_0207.jpg": {
        "probability": 0.15234029293060303
    },
    "frame_0208.jpg": {
        "probability": 0.15405374765396118
    },
    "frame_0209.jpg": {
        "probability": 0.11690212041139603
    },
    "frame_0210.jpg": {
        "probability": 0.10024350136518478
    },
    "frame_0211.jpg": {
        "probability": 0.05420118570327759
    },
    "frame_0212.jpg": {
        "probability": 0.051032837480306625
    },
    "frame_0213.jpg": {
        "probability": 0.050273045897483826
    },
    "frame_0214.jpg": {
        "probability": 0.05953085422515869
    },
    "frame_0215.jpg": {
        "probability": 0.08872511237859726
    },
    "frame_0216.jpg": {
        "probability": 0.03494998440146446
    },
    "frame_0217.jpg": {
        "probability": 0.04253298044204712
    },
    "frame_0218.jpg": {
        "probability": 0.05242648720741272
    },
    "frame_0219.jpg": {
        "probability": 0.048788025975227356
    },
    "frame_0220.jpg": {
        "probability": 0.06401564180850983
    },
    "frame_0221.jpg": {
        "probability": 0.06239977106451988
    },
    "frame_0222.jpg": {
        "probability": 0.024311989545822144
    },
    "frame_0223.jpg": {
        "probability": 0.016569385305047035
    },
    "frame_0224.jpg": {
        "probability": 0.008998528122901917
    },
    "frame_0225.jpg": {
        "probability": 0.022328486666083336
    },
    "frame_0226.jpg": {
        "probability": 0.015894439071416855
    },
    "frame_0227.jpg": {
        "probability": 0.005037282127887011
    },
    "frame_0228.jpg": {
        "probability": 0.03768724203109741
    },
    "frame_0229.jpg": {
        "probability": 0.034976135939359665
    },
    "frame_0230.jpg": {
        "probability": 0.01910153031349182
    },
    "frame_0231.jpg": {
        "probability": 0.0114189637824893
    },
    "frame_0232.jpg": {
        "probability": 0.01977653242647648
    },
    "frame_0233.jpg": {
        "probability": 0.035453736782073975
    },
    "frame_0234.jpg": {
        "probability": 0.04793750122189522
    },
    "frame_0235.jpg": {
        "probability": 0.04018952324986458
    },
    "frame_0236.jpg": {
        "probability": 0.05485844239592552
    },
    "frame_0237.jpg": {
        "probability": 0.04850371554493904
    },
    "frame_0238.jpg": {
        "probability": 0.04074890911579132
    },
    "frame_0239.jpg": {
        "probability": 0.022113937884569168
    },
    "frame_0240.jpg": {
        "probability": 0.010340973734855652
    },
    "frame_0241.jpg": {
        "probability": 0.02045135200023651
    },
    "frame_0242.jpg": {
        "probability": 0.015615807846188545
    },
    "frame_0243.jpg": {
        "probability": 0.013747848570346832
    },
    "frame_0244.jpg": {
        "probability": 0.013546166010200977
    },
    "frame_0245.jpg": {
        "probability": 0.012920023873448372
    },
    "frame_0246.jpg": {
        "probability": 0.018678046762943268
    },
    "frame_0247.jpg": {
        "probability": 0.01503591239452362
    },
    "frame_0248.jpg": {
        "probability": 0.023523546755313873
    },
    "frame_0249.jpg": {
        "probability": 0.031062409281730652
    },
    "frame_0250.jpg": {
        "probability": 0.019022677093744278
    },
    "frame_0251.jpg": {
        "probability": 0.011566962115466595
    },
    "frame_0252.jpg": {
        "probability": 0.01019585132598877
    },
    "frame_0253.jpg": {
        "probability": 0.008886889554560184
    },
    "frame_0254.jpg": {
        "probability": 0.016305668279528618
    },
    "frame_0255.jpg": {
        "probability": 0.02235270105302334
    },
    "frame_0256.jpg": {
        "probability": 0.016334565356373787
    },
    "frame_0257.jpg": {
        "probability": 0.007285238243639469
    },
    "frame_0258.jpg": {
        "probability": 0.006604555994272232
    },
    "frame_0259.jpg": {
        "probability": 0.010074405930936337
    },
    "frame_0260.jpg": {
        "probability": 0.005251709837466478
    },
    "frame_0261.jpg": {
        "probability": 0.008441099897027016
    },
    "frame_0262.jpg": {
        "probability": 0.006101802922785282
    },
    "frame_0263.jpg": {
        "probability": 0.008877758868038654
    },
    "frame_0264.jpg": {
        "probability": 0.006459326948970556
    },
    "frame_0265.jpg": {
        "probability": 0.0027224814984947443
    },
    "frame_0266.jpg": {
        "probability": 0.004331061616539955
    },
    "frame_0267.jpg": {
        "probability": 0.012729628011584282
    },
    "frame_0268.jpg": {
        "probability": 0.007704445160925388
    },
    "frame_0269.jpg": {
        "probability": 0.00423264829441905
    },
    "frame_0270.jpg": {
        "probability": 0.002751237014308572
    },
    "frame_0271.jpg": {
        "probability": 0.002484463155269623
    },
    "frame_0272.jpg": {
        "probability": 0.00650775246322155
    },
    "frame_0273.jpg": {
        "probability": 0.002748828148469329
    },
    "frame_0274.jpg": {
        "probability": 0.0027756746858358383
    },
    "frame_0275.jpg": {
        "probability": 0.0026040358934551477
    },
    "frame_0276.jpg": {
        "probability": 0.0016331598162651062
    },
    "frame_0277.jpg": {
        "probability": 0.0009888315107673407
    },
    "frame_0278.jpg": {
        "probability": 0.0007978368666954339
    },
    "frame_0279.jpg": {
        "probability": 0.000867811031639576
    },
    "frame_0280.jpg": {
        "probability": 0.0007846805965527892
    },
    "frame_0281.jpg": {
        "probability": 0.002436491660773754
    }
}